{
  "$schema": "https://developer.microsoft.com/json-schemas/fabric/item/report/definition/visualContainer/2.10.0/schema.json",
  "name": "v08ColSalarios",
  "position": {
    "x": 770,
    "y": 190,
    "z": 2001,
    "height": 480,
    "width": 480,
    "tabOrder": 7
  },
  "visual": {
    "visualType": "clusteredColumnChart",
    "query": {
      "queryState": {
        "Category": {
          "projections": [
            {
              "field": {
                "Column": {
                  "Expression": {
                    "SourceRef": {
                      "Entity": "Dim_Puestos"
                    }
                  },
                  "Property": "categoria_rol"
                }
              },
              "queryRef": "Dim_Puestos.categoria_rol",
              "nativeQueryRef": "categoria_rol",
              "active": true
            }
          ]
        },
        "Y": {
          "projections": [
            {
              "field": {
                "Measure": {
                  "Expression": {
                    "SourceRef": {
                      "Entity": "Medidas"
                    }
                  },
                  "Property": "Salario Mínimo Promedio"
                }
              },
              "queryRef": "Medidas.Salario Mínimo Promedio",
              "nativeQueryRef": "Salario Mínimo Promedio"
            },
            {
              "field": {
                "Measure": {
                  "Expression": {
                    "SourceRef": {
                      "Entity": "Medidas"
                    }
                  },
                  "Property": "Salario Máximo Promedio"
                }
              },
              "queryRef": "Medidas.Salario Máximo Promedio",
              "nativeQueryRef": "Salario Máximo Promedio"
            }
          ]
        }
      }
    },
    "drillFilterOtherVisuals": true
  }
}